{
  "matches": [
    {
      "src": "=>: => [1068,1070]",
      "dest": "=>: => [1913,1915]"
    },
    {
      "src": "parameter [2383,2403]",
      "dest": "parameter [2527,2549]"
    },
    {
      "src": "identifier: abi [2548,2551]",
      "dest": "identifier: abi [4672,4675]"
    },
    {
      "src": "(: ( [810,811]",
      "dest": "(: ( [1655,1656]"
    },
    {
      "src": "{: { [820,821]",
      "dest": "{: { [1665,1666]"
    },
    {
      "src": "{: { [1089,1090]",
      "dest": "{: { [1934,1935]"
    },
    {
      "src": "(: ( [1935,1936]",
      "dest": "(: ( [3525,3526]"
    },
    {
      "src": "): ) [1897,1898]",
      "dest": "): ) [4903,4904]"
    },
    {
      "src": "identifier: l2ToL1Messages [1186,1200]",
      "dest": "identifier: l2ToL1Messages [2031,2045]"
    },
    {
      "src": "(: ( [1026,1027]",
      "dest": "(: ( [1871,1872]"
    },
    {
      "src": "call_argument [1883,1890]",
      "dest": "call_argument [4896,4903]"
    },
    {
      "src": "): ) [1201,1202]",
      "dest": "): ) [2046,2047]"
    },
    {
      "src": "+=: += [2196,2198]",
      "dest": "+=: += [4321,4323]"
    },
    {
      "src": "identifier: to_address [2020,2030]",
      "dest": "identifier: toAddress [3622,3631]"
    },
    {
      "src": "expression_statement [2792,2823]",
      "dest": "expression_statement [4914,4945]"
    },
    {
      "src": "primitive_type [1245,1252]",
      "dest": "primitive_type [2090,2097]"
    },
    {
      "src": "}: } [996,997]",
      "dest": "}: } [1841,1842]"
    },
    {
      "src": "return_statement [830,863]",
      "dest": "return_statement [1675,1708]"
    },
    {
      "src": "identifier: msgHash [2218,2225]",
      "dest": "identifier: msgHash [4343,4350]"
    },
    {
      "src": "{: { [426,427]",
      "dest": "{: { [1022,1023]"
    },
    {
      "src": "+: + [1815,1816]",
      "dest": "+: + [4122,4123]"
    },
    {
      "src": "): ) [1163,1164]",
      "dest": "): ) [2008,2009]"
    },
    {
      "src": "primitive_type [1908,1915]",
      "dest": "primitive_type [4214,4221]"
    },
    {
      "src": "returns: returns [1393,1400]",
      "dest": "returns: returns [2238,2245]"
    },
    {
      "src": "call_argument [2129,2136]",
      "dest": "call_argument [3746,3753]"
    },
    {
      "src": "[: [ [853,854]",
      "dest": "[: [ [1698,1699]"
    },
    {
      "src": "(: ( [938,939]",
      "dest": "(: ( [1783,1784]"
    },
    {
      "src": "state_variable_declaration [665,741]",
      "dest": "state_variable_declaration [1261,1337]"
    },
    {
      "src": "calldata: calldata [2415,2423]",
      "dest": "calldata: calldata [4539,4547]"
    },
    {
      "src": ".: . [1292,1293]",
      "dest": ".: . [2137,2138]"
    },
    {
      "src": "inheritance_specifier [407,425]",
      "dest": "inheritance_specifier [1003,1021]"
    },
    {
      "src": ",: , [2760,2761]",
      "dest": ",: , [4166,4167]"
    },
    {
      "src": "string [2684,2712]",
      "dest": "string [4807,4835]"
    },
    {
      "src": "identifier: l2ToL1Messages [2792,2806]",
      "dest": "identifier: l2ToL1Messages [4914,4928]"
    },
    {
      "src": "function_definition [2353,2853]",
      "dest": "function_definition [4478,4975]"
    },
    {
      "src": "pure: pure [1038,1042]",
      "dest": "pure: pure [1883,1887]"
    },
    {
      "src": "parameter [1226,1261]",
      "dest": "parameter [2071,2106]"
    },
    {
      "src": "(: ( [1316,1317]",
      "dest": "(: ( [2161,2162]"
    },
    {
      "src": "parameter [1052,1087]",
      "dest": "parameter [1897,1932]"
    },
    {
      "src": "comment: /**       Consumes a message that was sent from an L2 contract.        Returns the hash of the message.     */ [2238,2348]",
      "dest": "comment: /**       Consumes a message that was sent from an L2 contract.        Returns the hash of the message.     */ [4363,4473]"
    },
    {
      "src": "\": \" [575,576]",
      "dest": "\": \" [1171,1172]"
    },
    {
      "src": "(: ( [1200,1201]",
      "dest": "(: ( [2045,2046]"
    },
    {
      "src": "returns: returns [1685,1692]",
      "dest": "returns: returns [3992,3999]"
    },
    {
      "src": "return: return [2211,2217]",
      "dest": "return: return [4336,4342]"
    },
    {
      "src": "): ) [2668,2669]",
      "dest": "): ) [4791,4792]"
    },
    {
      "src": "type_name [2405,2412]",
      "dest": "type_name [4529,4536]"
    },
    {
      "src": "identifier: msgHash [854,861]",
      "dest": "identifier: msgHash [1699,1706]"
    },
    {
      "src": ",: , [1871,1872]",
      "dest": ",: , [4894,4895]"
    },
    {
      "src": "identifier: L2L1_MESSAGE_MAP_TAG [1317,1337]",
      "dest": "identifier: L2L1_MESSAGE_MAP_TAG [2162,2182]"
    },
    {
      "src": "parameter [1634,1660]",
      "dest": "parameter [3941,3967]"
    },
    {
      "src": "[: [ [2669,2670]",
      "dest": "[: [ [4792,4793]"
    },
    {
      "src": "type_name [2405,2414]",
      "dest": "type_name [4529,4538]"
    },
    {
      "src": "expression_statement [2170,2201]",
      "dest": "expression_statement [4295,4326]"
    },
    {
      "src": "is: is [404,406]",
      "dest": "is: is [1000,1002]"
    },
    {
      "src": "call_argument [2565,2577]",
      "dest": "call_argument [4689,4700]"
    },
    {
      "src": "call_argument [1849,1859]",
      "dest": "call_argument [4884,4894]"
    },
    {
      "src": "function: function [1177,1185]",
      "dest": "function: function [2022,2030]"
    },
    {
      "src": "type_name [1071,1078]",
      "dest": "type_name [1916,1923]"
    },
    {
      "src": "type_name [1908,1915]",
      "dest": "type_name [4214,4221]"
    },
    {
      "src": "state_variable_declaration [497,577]",
      "dest": "state_variable_declaration [1093,1173]"
    },
    {
      "src": "identifier: L1L2_MESSAGE_NONCE_TAG [681,703]",
      "dest": "identifier: L1L2_MESSAGE_NONCE_TAG [1277,1299]"
    },
    {
      "src": "): ) [786,787]",
      "dest": "): ) [1631,1632]"
    },
    {
      "src": ",: , [2403,2404]",
      "dest": ",: , [4527,4528]"
    },
    {
      "src": "uint256: uint256 [1634,1641]",
      "dest": "uint256: uint256 [3941,3948]"
    },
    {
      "src": "]: ] [2677,2678]",
      "dest": "]: ] [4800,4801]"
    },
    {
      "src": "return_type_definition [1043,1088]",
      "dest": "return_type_definition [1888,1933]"
    },
    {
      "src": "\": \" [536,537]",
      "dest": "\": \" [1132,1133]"
    },
    {
      "src": "identifier: l1ToL2MessageNonce [1729,1747]",
      "dest": "identifier: l1ToL2MessageNonce [4036,4054]"
    },
    {
      "src": "override_specifier [2458,2466]",
      "dest": "override_specifier [4582,4590]"
    },
    {
      "src": "return_type_definition [1685,1702]",
      "dest": "return_type_definition [3992,4009]"
    },
    {
      "src": "=: = [1727,1728]",
      "dest": "=: = [4034,4035]"
    },
    {
      "src": "identifier: ConsumedMessageToL1 [2728,2747]",
      "dest": "identifier: LogMessageToL2 [4141,4155]"
    },
    {
      "src": "identifier: nonce [1892,1897]",
      "dest": "identifier: nonce [4198,4203]"
    },
    {
      "src": "contract: contract [377,385]",
      "dest": "contract: contract [973,981]"
    },
    {
      "src": "user_defined_type [407,425]",
      "dest": "user_defined_type [1003,1021]"
    },
    {
      "src": "member_expression [2097,2111]",
      "dest": "member_expression [3710,3724]"
    },
    {
      "src": "identifier: msgHash [907,914]",
      "dest": "identifier: msgHash [1752,1759]"
    },
    {
      "src": "(: ( [1747,1748]",
      "dest": "(: ( [4054,4055]"
    },
    {
      "src": "identifier: from_address [2391,2403]",
      "dest": "identifier: delayInSeconds [2535,2549]"
    },
    {
      "src": "type_name [1245,1252]",
      "dest": "type_name [2090,2097]"
    },
    {
      "src": "bytes32: bytes32 [1908,1915]",
      "dest": "bytes32: bytes32 [4214,4221]"
    },
    {
      "src": "import_directive [99,125]",
      "dest": "import_directive [662,694]"
    },
    {
      "src": ",: , [2614,2615]",
      "dest": ",: , [4737,4738]"
    },
    {
      "src": "(: ( [2564,2565]",
      "dest": "(: ( [4688,4689]"
    },
    {
      "src": "identifier: nonce [1809,1814]",
      "dest": "identifier: nonce [4116,4121]"
    },
    {
      "src": "function_body [948,997]",
      "dest": "function_body [1793,1842]"
    },
    {
      "src": "}: } [1344,1345]",
      "dest": "}: } [2189,2190]"
    },
    {
      "src": "identifier: from_address [2748,2760]",
      "dest": "identifier: toAddress [4168,4177]"
    },
    {
      "src": ".: . [2765,2766]",
      "dest": ".: . [4159,4160]"
    },
    {
      "src": "parameter [1608,1624]",
      "dest": "parameter [3915,3931]"
    },
    {
      "src": "call_expression [965,981]",
      "dest": "call_expression [1810,1826]"
    },
    {
      "src": "state_mutability [797,801]",
      "dest": "state_mutability [1642,1646]"
    },
    {
      "src": "{: { [1703,1704]",
      "dest": "{: { [4010,4011]"
    },
    {
      "src": "=: = [1924,1925]",
      "dest": "=: = [4230,4231]"
    },
    {
      "src": "): ) [1818,1819]",
      "dest": "): ) [4125,4126]"
    },
    {
      "src": "parameter [899,914]",
      "dest": "parameter [1744,1759]"
    },
    {
      "src": "(: ( [2806,2807]",
      "dest": "(: ( [4928,4929]"
    },
    {
      "src": "visibility [1203,1211]",
      "dest": "visibility [2048,2056]"
    },
    {
      "src": "call_argument [2748,2760]",
      "dest": "call_argument [4168,4177]"
    },
    {
      "src": "identifier: l1ToL2Messages [756,770]",
      "dest": "identifier: l1ToL2Messages [1601,1615]"
    },
    {
      "src": "function: function [1546,1554]",
      "dest": "function: function [3854,3862]"
    },
    {
      "src": "}: } [1170,1171]",
      "dest": "}: } [2015,2016]"
    },
    {
      "src": "internal: internal [1203,1211]",
      "dest": "internal: internal [2048,2056]"
    },
    {
      "src": "array_access [2170,2195]",
      "dest": "array_access [4295,4320]"
    },
    {
      "src": "identifier: abi [1949,1952]",
      "dest": "identifier: abi [3543,3546]"
    },
    {
      "src": "[: [ [981,982]",
      "dest": "[: [ [1826,1827]"
    },
    {
      "src": "(: ( [1693,1694]",
      "dest": "(: ( [4000,4001]"
    },
    {
      "src": ",: , [1598,1599]",
      "dest": ",: , [3905,3906]"
    },
    {
      "src": "call_argument [1873,1881]",
      "dest": "call_argument [4179,4187]"
    },
    {
      "src": "]: ] [2413,2414]",
      "dest": "]: ] [4537,4538]"
    },
    {
      "src": "comment: // SPDX-License-Identifier: Apache-2.0. [0,39]",
      "dest": "comment: // SPDX-License-Identifier: Apache-2.0. [596,635]"
    },
    {
      "src": "function_body [1263,1345]",
      "dest": "function_body [2108,2190]"
    },
    {
      "src": "string: string [582,588]",
      "dest": "string: string [1178,1184]"
    },
    {
      "src": "function_definition [1351,1484]",
      "dest": "function_definition [2196,2329]"
    },
    {
      "src": "identifier: l1ToL2Messages [837,851]",
      "dest": "identifier: l1ToL2Messages [1682,1696]"
    },
    {
      "src": "number_literal: 1 [2821,2822]",
      "dest": "number_literal: 1 [4943,4944]"
    },
    {
      "src": "}: } [2852,2853]",
      "dest": "}: } [4974,4975]"
    },
    {
      "src": "import: import [99,105]",
      "dest": "import: import [662,668]"
    },
    {
      "src": "identifier: getUintValue [1441,1453]",
      "dest": "identifier: getUintValue [2286,2298]"
    },
    {
      "src": "identifier: L1L2_MESSAGE_MAP_TAG [513,533]",
      "dest": "identifier: L1L2_MESSAGE_MAP_TAG [1109,1129]"
    },
    {
      "src": "\": \" [621,622]",
      "dest": "\": \" [1217,1218]"
    },
    {
      "src": ".: . [1994,1995]",
      "dest": ".: . [3592,3593]"
    },
    {
      "src": "identifier: nonce [1721,1726]",
      "dest": "identifier: nonce [4028,4033]"
    },
    {
      "src": ".: . [1118,1119]",
      "dest": ".: . [1963,1964]"
    },
    {
      "src": "uint256: uint256 [1580,1587]",
      "dest": "uint256: uint256 [3351,3358]"
    },
    {
      "src": "\": \" [657,658]",
      "dest": "\": \" [1253,1254]"
    },
    {
      "src": "storage: storage [1080,1087]",
      "dest": "storage: storage [1925,1932]"
    },
    {
      "src": "call_expression [2525,2634]",
      "dest": "call_expression [4649,4757]"
    },
    {
      "src": "returns: returns [1217,1224]",
      "dest": "returns: returns [2062,2069]"
    },
    {
      "src": "primitive_type [899,906]",
      "dest": "primitive_type [1744,1751]"
    },
    {
      "src": "type_cast_expression [2579,2598]",
      "dest": "type_cast_expression [4702,4721]"
    },
    {
      "src": "-=: -= [2818,2820]",
      "dest": "-=: -= [4940,4942]"
    },
    {
      "src": "(: ( [2483,2484]",
      "dest": "(: ( [4607,4608]"
    },
    {
      "src": "call_expression [1949,2150]",
      "dest": "call_expression [3543,3771]"
    },
    {
      "src": "(: ( [2652,2653]",
      "dest": "(: ( [4775,4776]"
    },
    {
      "src": "string [706,740]",
      "dest": "string [1302,1336]"
    },
    {
      "src": ">: > [2679,2680]",
      "dest": ">: > [4802,4803]"
    },
    {
      "src": "returns: returns [1043,1050]",
      "dest": "returns: returns [1888,1895]"
    },
    {
      "src": "identifier: l2ToL1Messages [965,979]",
      "dest": "identifier: l2ToL1Messages [1810,1824]"
    },
    {
      "src": "string [621,658]",
      "dest": "string [1217,1254]"
    },
    {
      "src": ".: . [2104,2105]",
      "dest": ".: . [3717,3718]"
    },
    {
      "src": ",: , [2053,2054]",
      "dest": ",: , [3658,3659]"
    },
    {
      "src": "}: } [1483,1484]",
      "dest": "}: } [2328,2329]"
    },
    {
      "src": "): ) [1078,1079]",
      "dest": "): ) [1923,1924]"
    },
    {
      "src": "identifier: msg [1991,1994]",
      "dest": "identifier: msg [3589,3592]"
    },
    {
      "src": "): ) [2712,2713]",
      "dest": "): ) [4835,4836]"
    },
    {
      "src": "constant: constant [504,512]",
      "dest": "constant: constant [1100,1108]"
    },
    {
      "src": "external: external [2441,2449]",
      "dest": "external: external [4565,4573]"
    },
    {
      "src": "identifier: payload [1653,1660]",
      "dest": "identifier: payload [3960,3967]"
    },
    {
      "src": "(: ( [851,852]",
      "dest": "(: ( [1696,1697]"
    },
    {
      "src": "solidity_pragma_token [47,63]",
      "dest": "solidity_pragma_token [643,659]"
    },
    {
      "src": "variable_declaration_statement [2507,2635]",
      "dest": "variable_declaration_statement [4631,4758]"
    },
    {
      "src": ",: , [1807,1808]",
      "dest": ",: , [4114,4115]"
    },
    {
      "src": "array_access [2792,2817]",
      "dest": "array_access [4914,4939]"
    },
    {
      "src": "call_argument [1861,1871]",
      "dest": "call_argument [4871,4882]"
    },
    {
      "src": "call_argument [1809,1818]",
      "dest": "call_argument [4116,4125]"
    },
    {
      "src": "identifier: L1L2_MESSAGE_MAP_TAG [1143,1163]",
      "dest": "identifier: L1L2_MESSAGE_MAP_TAG [1988,2008]"
    },
    {
      "src": "return_type_definition [1393,1410]",
      "dest": "return_type_definition [2238,2255]"
    },
    {
      "src": "type_name [2383,2390]",
      "dest": "type_name [2527,2534]"
    },
    {
      "src": "type_name [1634,1641]",
      "dest": "type_name [3941,3948]"
    },
    {
      "src": "identifier: l2ToL1Messages [2653,2667]",
      "dest": "identifier: l2ToL1Messages [4776,4790]"
    },
    {
      "src": "function_body [1089,1171]",
      "dest": "function_body [1934,2016]"
    },
    {
      "src": "identifier: selector [1873,1881]",
      "dest": "identifier: selector [4179,4187]"
    },
    {
      "src": "primitive_type [2383,2390]",
      "dest": "primitive_type [2527,2534]"
    },
    {
      "src": "member_expression [1991,2001]",
      "dest": "member_expression [3589,3599]"
    },
    {
      "src": "\": \" [739,740]",
      "dest": "\": \" [1335,1336]"
    },
    {
      "src": "primitive_type [1402,1409]",
      "dest": "primitive_type [2247,2254]"
    },
    {
      "src": "primitive_type [771,778]",
      "dest": "primitive_type [1616,1623]"
    },
    {
      "src": "identifier: msgHash [779,786]",
      "dest": "identifier: msgHash [1624,1631]"
    },
    {
      "src": "identifier: sender [2766,2772]",
      "dest": "identifier: sender [4160,4166]"
    },
    {
      "src": "variable_declaration_statement [1908,2161]",
      "dest": "variable_declaration_statement [4214,4286]"
    },
    {
      "src": ",: , [2111,2112]",
      "dest": ",: , [3724,3725]"
    },
    {
      "src": "(: ( [898,899]",
      "dest": "(: ( [1743,1744]"
    },
    {
      "src": "variable_declaration_statement [1713,1750]",
      "dest": "variable_declaration_statement [4020,4057]"
    },
    {
      "src": "bytes32: bytes32 [2507,2514]",
      "dest": "bytes32: bytes32 [4631,4638]"
    },
    {
      "src": "call_argument [2579,2598]",
      "dest": "call_argument [4702,4721]"
    },
    {
      "src": "uint256: uint256 [2579,2586]",
      "dest": "uint256: uint256 [4702,4709]"
    },
    {
      "src": "primitive_type [1983,1990]",
      "dest": "primitive_type [3581,3588]"
    },
    {
      "src": "primitive_type [2507,2514]",
      "dest": "primitive_type [4631,4638]"
    },
    {
      "src": "function: function [747,755]",
      "dest": "function: function [1592,1600]"
    },
    {
      "src": "(: ( [2534,2535]",
      "dest": "(: ( [4658,4659]"
    },
    {
      "src": "visibility [1029,1037]",
      "dest": "visibility [1874,1882]"
    },
    {
      "src": "): ) [2633,2634]",
      "dest": "): ) [4756,4757]"
    },
    {
      "src": "array_access [837,862]",
      "dest": "array_access [1682,1707]"
    },
    {
      "src": "identifier: msgHash [1916,1923]",
      "dest": "identifier: msgHash [4222,4229]"
    },
    {
      "src": "visibility [788,796]",
      "dest": "visibility [1633,1641]"
    },
    {
      "src": "identifier: payload [2616,2623]",
      "dest": "identifier: payload [4739,4746]"
    },
    {
      "src": "): ) [1409,1410]",
      "dest": "): ) [2254,2255]"
    },
    {
      "src": "parameter [1694,1701]",
      "dest": "parameter [4001,4008]"
    },
    {
      "src": "uint256: uint256 [1608,1615]",
      "dest": "uint256: uint256 [3915,3922]"
    },
    {
      "src": "identifier: msg [1849,1852]",
      "dest": "identifier: msg [4884,4887]"
    },
    {
      "src": "(: ( [1401,1402]",
      "dest": "(: ( [2246,2247]"
    },
    {
      "src": "): ) [1665,1666]",
      "dest": "): ) [3972,3973]"
    },
    {
      "src": "call_expression [2792,2808]",
      "dest": "call_expression [4914,4930]"
    },
    {
      "src": "member_expression [2587,2597]",
      "dest": "member_expression [4710,4720]"
    },
    {
      "src": "): ) [2149,2150]",
      "dest": "): ) [3770,3771]"
    },
    {
      "src": "identifier: IStarknetMessaging [407,425]",
      "dest": "identifier: IStarknetMessaging [1003,1021]"
    },
    {
      "src": "identifier: selector [1616,1624]",
      "dest": "identifier: selector [3923,3931]"
    },
    {
      "src": "function_definition [875,997]",
      "dest": "function_definition [1720,1842]"
    },
    {
      "src": "contract_body [426,2855]",
      "dest": "contract_body [1022,6417]"
    },
    {
      "src": "expression_statement [2645,2714]",
      "dest": "expression_statement [4768,4837]"
    },
    {
      "src": "emit_statement [2723,2783]",
      "dest": "emit_statement [4136,4205]"
    },
    {
      "src": "identifier: l1ToL2Messages [2170,2184]",
      "dest": "identifier: l1ToL2Messages [4295,4309]"
    },
    {
      "src": ",: , [2682,2683]",
      "dest": ",: , [4805,4806]"
    },
    {
      "src": "identifier: NamedStorage [1106,1118]",
      "dest": "identifier: NamedStorage [1951,1963]"
    },
    {
      "src": "\": \" [123,124]",
      "dest": "\": \" [692,693]"
    },
    {
      "src": "): ) [980,981]",
      "dest": "): ) [1825,1826]"
    },
    {
      "src": "=>: => [1242,1244]",
      "dest": "=>: => [2087,2089]"
    },
    {
      "src": "[: [ [2808,2809]",
      "dest": "[: [ [4930,4931]"
    },
    {
      "src": "primitive_type [1608,1615]",
      "dest": "primitive_type [3915,3922]"
    },
    {
      "src": "return: return [1421,1427]",
      "dest": "return: return [2266,2272]"
    },
    {
      "src": "call_argument [1892,1897]",
      "dest": "call_argument [4198,4203]"
    },
    {
      "src": "emit: emit [1829,1833]",
      "dest": "emit: emit [4846,4850]"
    },
    {
      "src": "identifier: payload [2129,2136]",
      "dest": "identifier: payload [3746,3753]"
    },
    {
      "src": "call_expression [1428,1477]",
      "dest": "call_expression [2273,2322]"
    },
    {
      "src": "identifier: payload [2424,2431]",
      "dest": "identifier: payload [4548,4555]"
    },
    {
      "src": "return_statement [958,991]",
      "dest": "return_statement [1803,1836]"
    },
    {
      "src": "override: override [2458,2466]",
      "dest": "override: override [4582,4590]"
    },
    {
      "src": "identifier: LogMessageToL2 [1834,1848]",
      "dest": "identifier: ConsumedMessageToL1 [4851,4870]"
    },
    {
      "src": "augmented_assignment_expression [2792,2822]",
      "dest": "augmented_assignment_expression [4914,4944]"
    },
    {
      "src": "parameter [1402,1409]",
      "dest": "parameter [2247,2254]"
    },
    {
      "src": "solidity_version_comparison_operator [55,57]",
      "dest": "solidity_version_comparison_operator [651,653]"
    },
    {
      "src": "bytes32: bytes32 [2484,2491]",
      "dest": "bytes32: bytes32 [4608,4615]"
    },
    {
      "src": "^:  ^ [55,57]",
      "dest": "^:  ^ [651,653]"
    },
    {
      "src": "(: ( [1453,1454]",
      "dest": "(: ( [2298,2299]"
    },
    {
      "src": "(: ( [2747,2748]",
      "dest": "(: ( [4155,4156]"
    },
    {
      "src": "type_name [2507,2514]",
      "dest": "type_name [4631,4638]"
    },
    {
      "src": "identifier: length [2105,2111]",
      "dest": "identifier: length [3718,3724]"
    },
    {
      "src": "identifier: length [2608,2614]",
      "dest": "identifier: length [4731,4737]"
    },
    {
      "src": "uint256: uint256 [1402,1409]",
      "dest": "uint256: uint256 [2247,2254]"
    },
    {
      "src": "solidity_version: 0.6.12 [57,63]",
      "dest": "solidity_version: 0.6.12 [653,659]"
    },
    {
      "src": "identifier: l1ToL2Messages [1012,1026]",
      "dest": "identifier: l1ToL2Messages [1857,1871]"
    },
    {
      "src": "uint256: uint256 [1713,1720]",
      "dest": "uint256: uint256 [4020,4027]"
    },
    {
      "src": "calldata: calldata [1644,1652]",
      "dest": "calldata: calldata [3951,3959]"
    },
    {
      "src": "member_expression [1280,1316]",
      "dest": "member_expression [2125,2161]"
    },
    {
      "src": "identifier: consumeMessageFromL2 [2362,2382]",
      "dest": "identifier: consumeMessageFromL2 [4487,4507]"
    },
    {
      "src": "call_expression [2653,2669]",
      "dest": "call_expression [4776,4792]"
    },
    {
      "src": "): ) [1379,1380]",
      "dest": "): ) [2224,2225]"
    },
    {
      "src": "(: ( [979,980]",
      "dest": "(: ( [1824,1825]"
    },
    {
      "src": "primitive_type [1634,1641]",
      "dest": "primitive_type [3941,3948]"
    },
    {
      "src": "[: [ [1641,1642]",
      "dest": "[: [ [3948,3949]"
    },
    {
      "src": "return_type_definition [802,819]",
      "dest": "return_type_definition [1647,1664]"
    },
    {
      "src": "identifier: sender [2591,2597]",
      "dest": "identifier: sender [4714,4720]"
    },
    {
      "src": "state_mutability [1038,1042]",
      "dest": "state_mutability [1883,1887]"
    },
    {
      "src": "return: return [958,964]",
      "dest": "return: return [1803,1809]"
    },
    {
      "src": "identifier: keccak256 [1926,1935]",
      "dest": "identifier: keccak256 [3516,3525]"
    },
    {
      "src": "returns: returns [930,937]",
      "dest": "returns: returns [1775,1782]"
    },
    {
      "src": "call_argument [2774,2781]",
      "dest": "call_argument [4189,4196]"
    },
    {
      "src": "member_expression [1759,1784]",
      "dest": "member_expression [4066,4091]"
    },
    {
      "src": "member_expression [2548,2564]",
      "dest": "member_expression [4672,4688]"
    },
    {
      "src": "type_name [1226,1253]",
      "dest": "type_name [2071,2098]"
    },
    {
      "src": "internal: internal [1029,1037]",
      "dest": "internal: internal [1874,1882]"
    },
    {
      "src": "identifier: to_address [1861,1871]",
      "dest": "identifier: fromAddress [4871,4882]"
    },
    {
      "src": "type_name [899,906]",
      "dest": "type_name [1744,1751]"
    },
    {
      "src": "): ) [1261,1262]",
      "dest": "): ) [2106,2107]"
    },
    {
      "src": "visibility [916,924]",
      "dest": "visibility [1761,1769]"
    },
    {
      "src": "type_name [811,818]",
      "dest": "type_name [1656,1663]"
    },
    {
      "src": "]: ] [989,990]",
      "dest": "]: ] [1834,1835]"
    },
    {
      "src": "augmented_assignment_expression [2170,2200]",
      "dest": "augmented_assignment_expression [4295,4325]"
    },
    {
      "src": "[: [ [2186,2187]",
      "dest": "[: [ [4311,4312]"
    },
    {
      "src": "call_expression [2170,2186]",
      "dest": "call_expression [4295,4311]"
    },
    {
      "src": "): ) [1476,1477]",
      "dest": "): ) [2321,2322]"
    },
    {
      "src": "function_definition [1003,1171]",
      "dest": "function_definition [1848,2016]"
    },
    {
      "src": "{: { [948,949]",
      "dest": "{: { [1793,1794]"
    },
    {
      "src": "identifier: msgHash [2187,2194]",
      "dest": "identifier: msgHash [4312,4319]"
    },
    {
      "src": "string [536,576]",
      "dest": "string [1132,1172]"
    },
    {
      "src": "]: ] [2816,2817]",
      "dest": "]: ] [4938,4939]"
    },
    {
      "src": "(: ( [1570,1571]",
      "dest": "(: ( [3878,3879]"
    },
    {
      "src": "): ) [2159,2160]",
      "dest": "): ) [3784,3785]"
    },
    {
      "src": ".: . [1771,1772]",
      "dest": ".: . [4078,4079]"
    },
    {
      "src": "function_body [2497,2853]",
      "dest": "function_body [4621,4975]"
    },
    {
      "src": "type_name [939,946]",
      "dest": "type_name [1784,1791]"
    },
    {
      "src": "external: external [788,796]",
      "dest": "external: external [1633,1641]"
    },
    {
      "src": "primitive_type [1713,1720]",
      "dest": "primitive_type [4020,4027]"
    },
    {
      "src": "identifier: payload [2097,2104]",
      "dest": "identifier: payload [3710,3717]"
    },
    {
      "src": "identifier: NamedStorage [1428,1440]",
      "dest": "identifier: NamedStorage [2273,2285]"
    },
    {
      "src": "identifier: from_address [2565,2577]",
      "dest": "identifier: fromAddress [4689,4700]"
    },
    {
      "src": "type_cast_expression [1983,2002]",
      "dest": "type_cast_expression [3581,3600]"
    },
    {
      "src": "expression_statement [1759,1820]",
      "dest": "expression_statement [4066,4127]"
    },
    {
      "src": "storage: storage [1254,1261]",
      "dest": "storage: storage [2099,2106]"
    },
    {
      "src": "member_expression [1849,1859]",
      "dest": "member_expression [4884,4894]"
    },
    {
      "src": "bytes32: bytes32 [1694,1701]",
      "dest": "bytes32: bytes32 [4001,4008]"
    },
    {
      "src": "(: ( [1225,1226]",
      "dest": "(: ( [2070,2071]"
    },
    {
      "src": "type_name [1608,1615]",
      "dest": "type_name [3915,3922]"
    },
    {
      "src": "primitive_type [1234,1241]",
      "dest": "primitive_type [2079,2086]"
    },
    {
      "src": "view: view [1388,1392]",
      "dest": "view: view [2233,2237]"
    },
    {
      "src": "parameter [2484,2491]",
      "dest": "parameter [4608,4615]"
    },
    {
      "src": "uint256: uint256 [811,818]",
      "dest": "uint256: uint256 [1656,1663]"
    },
    {
      "src": "pragma: pragma [40,46]",
      "dest": "pragma: pragma [636,642]"
    },
    {
      "src": "function_body [1411,1484]",
      "dest": "function_body [2256,2329]"
    },
    {
      "src": "): ) [1748,1749]",
      "dest": "): ) [4055,4056]"
    },
    {
      "src": "return_type_definition [2475,2492]",
      "dest": "return_type_definition [4599,4616]"
    },
    {
      "src": "(: ( [2382,2383]",
      "dest": "(: ( [4507,4508]"
    },
    {
      "src": "bytes32: bytes32 [771,778]",
      "dest": "bytes32: bytes32 [1616,1623]"
    },
    {
      "src": "identifier: sendMessageToL2 [1555,1570]",
      "dest": "identifier: sendMessageToL2 [3863,3878]"
    },
    {
      "src": "identifier: setUintValue [1772,1784]",
      "dest": "identifier: setUintValue [4079,4091]"
    },
    {
      "src": "binary_expression [2653,2682]",
      "dest": "binary_expression [4776,4805]"
    },
    {
      "src": "primitive_type [939,946]",
      "dest": "primitive_type [1784,1791]"
    },
    {
      "src": "=: = [704,705]",
      "dest": "=: = [1300,1301]"
    },
    {
      "src": "identifier: L2L1_MESSAGE_MAP_TAG [598,618]",
      "dest": "identifier: L2L1_MESSAGE_MAP_TAG [1194,1214]"
    },
    {
      "src": "call_argument [2587,2597]",
      "dest": "call_argument [4710,4720]"
    },
    {
      "src": "public: public [1381,1387]",
      "dest": "public: public [2226,2232]"
    },
    {
      "src": "call_expression [1759,1819]",
      "dest": "call_expression [4066,4126]"
    },
    {
      "src": "call_argument [2548,2624]",
      "dest": "call_argument [4672,4747]"
    },
    {
      "src": "call_argument [2097,2111]",
      "dest": "call_argument [3710,3724]"
    },
    {
      "src": "\": \" [96,97]",
      "dest": "\": \" [719,720]"
    },
    {
      "src": ",: , [1859,1860]",
      "dest": ",: , [4882,4883]"
    },
    {
      "src": "member_expression [2600,2614]",
      "dest": "member_expression [4723,4737]"
    },
    {
      "src": "identifier: selector [2071,2079]",
      "dest": "identifier: selector [3680,3688]"
    },
    {
      "src": "): ) [1087,1088]",
      "dest": "): ) [1932,1933]"
    },
    {
      "src": "identifier: bytes32ToUint256Mapping [1119,1142]",
      "dest": "identifier: bytes32ToUint256Mapping [1964,1987]"
    },
    {
      "src": "identifier: L1L2_MESSAGE_NONCE_TAG [1785,1807]",
      "dest": "identifier: L1L2_MESSAGE_NONCE_TAG [4092,4114]"
    },
    {
      "src": "binary_expression [1809,1818]",
      "dest": "binary_expression [4116,4125]"
    },
    {
      "src": "): ) [2597,2598]",
      "dest": "): ) [4720,4721]"
    },
    {
      "src": "state_mutability [925,929]",
      "dest": "state_mutability [1770,1774]"
    },
    {
      "src": "identifier: msgHash [2839,2846]",
      "dest": "identifier: msgHash [4961,4968]"
    },
    {
      "src": "return: return [2832,2838]",
      "dest": "return: return [4954,4960]"
    },
    {
      "src": "identifier: keccak256 [2525,2534]",
      "dest": "identifier: keccak256 [4649,4658]"
    },
    {
      "src": "override_specifier [1676,1684]",
      "dest": "override_specifier [3983,3991]"
    },
    {
      "src": "return: return [830,836]",
      "dest": "return: return [1675,1681]"
    },
    {
      "src": "type_name [1694,1701]",
      "dest": "type_name [4001,4008]"
    },
    {
      "src": ",: , [2030,2031]",
      "dest": ",: , [3631,3632]"
    },
    {
      "src": "identifier: payload [2774,2781]",
      "dest": "identifier: payload [4189,4196]"
    },
    {
      "src": "returns: returns [802,809]",
      "dest": "returns: returns [1647,1654]"
    },
    {
      "src": "identifier: NamedStorage [1759,1771]",
      "dest": "identifier: NamedStorage [4066,4078]"
    },
    {
      "src": "(: ( [1784,1785]",
      "dest": "(: ( [4091,4092]"
    },
    {
      "src": "type_name [1052,1079]",
      "dest": "type_name [1897,1924]"
    },
    {
      "src": "visibility [1381,1387]",
      "dest": "visibility [2226,2232]"
    },
    {
      "src": "): ) [1337,1338]",
      "dest": "): ) [2182,2183]"
    },
    {
      "src": "(: ( [1848,1849]",
      "dest": "(: ( [4870,4871]"
    },
    {
      "src": "identifier: encodePacked [1953,1965]",
      "dest": "identifier: encodePacked [3547,3559]"
    },
    {
      "src": "}: } [868,869]",
      "dest": "}: } [1713,1714]"
    },
    {
      "src": "identifier: L1L2_MESSAGE_NONCE_TAG [1454,1476]",
      "dest": "identifier: L1L2_MESSAGE_NONCE_TAG [2299,2321]"
    },
    {
      "src": "comment: /**       Sends a message to an L2 contract.     */ [1490,1541]",
      "dest": "comment: /**       Sends a message to an L2 contract.     */ [3798,3849]"
    },
    {
      "src": "call_argument [1949,2150]",
      "dest": "call_argument [3543,3771]"
    },
    {
      "src": ".: . [2590,2591]",
      "dest": ".: . [4713,4714]"
    },
    {
      "src": "(: ( [1378,1379]",
      "dest": "(: ( [2223,2224]"
    },
    {
      "src": "call_expression [1106,1164]",
      "dest": "call_expression [1951,2009]"
    },
    {
      "src": "type_name [1402,1409]",
      "dest": "type_name [2247,2254]"
    },
    {
      "src": "string [106,124]",
      "dest": "string [669,693]"
    },
    {
      "src": "import_directive [66,98]",
      "dest": "import_directive [695,721]"
    },
    {
      "src": "call_argument [1983,2002]",
      "dest": "call_argument [3581,3600]"
    },
    {
      "src": "): ) [2623,2624]",
      "dest": "): ) [4746,4747]"
    },
    {
      "src": "member_expression [1428,1453]",
      "dest": "member_expression [2273,2298]"
    },
    {
      "src": "primitive_type [2405,2412]",
      "dest": "primitive_type [4529,4536]"
    },
    {
      "src": "emit_statement [1829,1899]",
      "dest": "emit_statement [4846,4905]"
    },
    {
      "src": "call_argument [2762,2772]",
      "dest": "call_argument [4156,4166]"
    },
    {
      "src": "contract_declaration [377,2855]",
      "dest": "contract_declaration [973,6417]"
    },
    {
      "src": "): ) [2807,2808]",
      "dest": "): ) [4929,4930]"
    },
    {
      "src": "type_name [665,671]",
      "dest": "type_name [1261,1267]"
    },
    {
      "src": "source_file [0,2856]",
      "dest": "source_file [0,6418]"
    },
    {
      "src": ",: , [2577,2578]",
      "dest": ",: , [4700,4701]"
    },
    {
      "src": "mapping: mapping [1052,1059]",
      "dest": "mapping: mapping [1897,1904]"
    },
    {
      "src": "type_name [771,778]",
      "dest": "type_name [1616,1623]"
    },
    {
      "src": "visibility [2441,2449]",
      "dest": "visibility [4565,4573]"
    },
    {
      "src": ",: , [2002,2003]",
      "dest": ",: , [3600,3601]"
    },
    {
      "src": "type_name [1634,1643]",
      "dest": "type_name [3941,3950]"
    },
    {
      "src": "pragma_directive [40,64]",
      "dest": "pragma_directive [636,660]"
    },
    {
      "src": ",: , [1624,1625]",
      "dest": ",: , [3931,3932]"
    },
    {
      "src": "{: { [2497,2498]",
      "dest": "{: { [4621,4622]"
    },
    {
      "src": "number_literal: 0 [2681,2682]",
      "dest": "number_literal: 0 [4804,4805]"
    },
    {
      "src": "string: string [665,671]",
      "dest": "string: string [1261,1267]"
    },
    {
      "src": "identifier: StarknetMessaging [386,403]",
      "dest": "identifier: StarknetMessaging [982,999]"
    },
    {
      "src": "bytes32: bytes32 [899,906]",
      "dest": "bytes32: bytes32 [1744,1751]"
    },
    {
      "src": "identifier: l1ToL2MessageNonce [1360,1378]",
      "dest": "identifier: l1ToL2MessageNonce [2205,2223]"
    },
    {
      "src": "(: ( [2184,2185]",
      "dest": "(: ( [4309,4310]"
    },
    {
      "src": "primitive_type [497,503]",
      "dest": "primitive_type [1093,1099]"
    },
    {
      "src": "{: { [1263,1264]",
      "dest": "{: { [2108,2109]"
    },
    {
      "src": "uint256: uint256 [939,946]",
      "dest": "uint256: uint256 [1784,1791]"
    },
    {
      "src": "variable_declaration [1713,1726]",
      "dest": "variable_declaration [4020,4033]"
    },
    {
      "src": "call_argument [2653,2682]",
      "dest": "call_argument [4776,4805]"
    },
    {
      "src": "]: ] [1642,1643]",
      "dest": "]: ] [3949,3950]"
    },
    {
      "src": "identifier: NamedStorage [1280,1292]",
      "dest": "identifier: NamedStorage [2125,2137]"
    },
    {
      "src": "call_expression [2645,2713]",
      "dest": "call_expression [4768,4836]"
    },
    {
      "src": "string_literal [536,576]",
      "dest": "string_literal [1132,1172]"
    },
    {
      "src": "mapping: mapping [1226,1233]",
      "dest": "mapping: mapping [2071,2078]"
    },
    {
      "src": ".: . [1952,1953]",
      "dest": ".: . [3546,3547]"
    },
    {
      "src": "call_argument [2684,2712]",
      "dest": "call_argument [4807,4835]"
    },
    {
      "src": "identifier: require [2645,2652]",
      "dest": "identifier: require [4768,4775]"
    },
    {
      "src": "}: } [2854,2855]",
      "dest": "}: } [6416,6417]"
    },
    {
      "src": "pure: pure [1212,1216]",
      "dest": "pure: pure [2057,2061]"
    },
    {
      "src": "): ) [2781,2782]",
      "dest": "): ) [4203,4204]"
    },
    {
      "src": "primitive_type [1071,1078]",
      "dest": "primitive_type [1916,1923]"
    },
    {
      "src": "): ) [946,947]",
      "dest": "): ) [1791,1792]"
    },
    {
      "src": "identifier: msgHash [2809,2816]",
      "dest": "identifier: msgHash [4931,4938]"
    },
    {
      "src": "(: ( [1233,1234]",
      "dest": "(: ( [2078,2079]"
    },
    {
      "src": "return_statement [2832,2847]",
      "dest": "return_statement [4954,4969]"
    },
    {
      "src": "): ) [2185,2186]",
      "dest": "): ) [4310,4311]"
    },
    {
      "src": "(: ( [1051,1052]",
      "dest": "(: ( [1896,1897]"
    },
    {
      "src": "uint256: uint256 [1245,1252]",
      "dest": "uint256: uint256 [2090,2097]"
    },
    {
      "src": "identifier: payload [2600,2607]",
      "dest": "identifier: payload [4723,4730]"
    },
    {
      "src": "uint256: uint256 [2383,2390]",
      "dest": "uint256: uint256 [2527,2534]"
    },
    {
      "src": "return: return [1099,1105]",
      "dest": "return: return [1944,1950]"
    },
    {
      "src": "call_argument [2020,2030]",
      "dest": "call_argument [3622,3631]"
    },
    {
      "src": "identifier: l2ToL1Messages [884,898]",
      "dest": "identifier: l2ToL1Messages [1729,1743]"
    },
    {
      "src": "(: ( [1142,1143]",
      "dest": "(: ( [1987,1988]"
    },
    {
      "src": "primitive_type [2579,2586]",
      "dest": "primitive_type [4702,4709]"
    },
    {
      "src": "return_statement [1099,1165]",
      "dest": "return_statement [1944,2010]"
    },
    {
      "src": "function_body [820,869]",
      "dest": "function_body [1665,1714]"
    },
    {
      "src": "return_type_definition [930,947]",
      "dest": "return_type_definition [1775,1792]"
    },
    {
      "src": "identifier: bytes32ToUint256Mapping [1293,1316]",
      "dest": "identifier: bytes32ToUint256Mapping [2138,2161]"
    },
    {
      "src": "call_argument [1991,2001]",
      "dest": "call_argument [3589,3599]"
    },
    {
      "src": "identifier: msg [2762,2765]",
      "dest": "identifier: msg [4156,4159]"
    },
    {
      "src": "import: import [66,72]",
      "dest": "import: import [695,701]"
    },
    {
      "src": "visibility [1667,1675]",
      "dest": "visibility [3974,3982]"
    },
    {
      "src": "call_argument [1454,1476]",
      "dest": "call_argument [2299,2321]"
    },
    {
      "src": "=: = [2523,2524]",
      "dest": "=: = [4647,4648]"
    },
    {
      "src": "\": \" [73,74]",
      "dest": "\": \" [702,703]"
    },
    {
      "src": "): ) [1252,1253]",
      "dest": "): ) [2097,2098]"
    },
    {
      "src": "): ) [2001,2002]",
      "dest": "): ) [3599,3600]"
    },
    {
      "src": "uint256: uint256 [2405,2412]",
      "dest": "uint256: uint256 [4529,4536]"
    },
    {
      "src": "identifier: sender [1853,1859]",
      "dest": "identifier: sender [4888,4894]"
    },
    {
      "src": "=: = [619,620]",
      "dest": "=: = [1215,1216]"
    },
    {
      "src": "(: ( [2667,2668]",
      "dest": "(: ( [4790,4791]"
    },
    {
      "src": "type_name [497,503]",
      "dest": "type_name [1093,1099]"
    },
    {
      "src": ".: . [2607,2608]",
      "dest": ".: . [4730,4731]"
    },
    {
      "src": "variable_declaration [2507,2522]",
      "dest": "variable_declaration [4631,4646]"
    },
    {
      "src": "call_argument [2600,2614]",
      "dest": "call_argument [4723,4737]"
    },
    {
      "src": "array_access [2653,2678]",
      "dest": "array_access [4776,4801]"
    },
    {
      "src": "return_statement [1421,1478]",
      "dest": "return_statement [2266,2323]"
    },
    {
      "src": "variable_declaration [1908,1923]",
      "dest": "variable_declaration [4214,4229]"
    },
    {
      "src": "bytes32: bytes32 [1060,1067]",
      "dest": "bytes32: bytes32 [1905,1912]"
    },
    {
      "src": "): ) [852,853]",
      "dest": "): ) [1697,1698]"
    },
    {
      "src": "function: function [1003,1011]",
      "dest": "function: function [1848,1856]"
    },
    {
      "src": "call_expression [1926,2160]",
      "dest": "call_expression [3516,3785]"
    },
    {
      "src": "state_mutability [1212,1216]",
      "dest": "state_mutability [2057,2061]"
    },
    {
      "src": "(: ( [1059,1060]",
      "dest": "(: ( [1904,1905]"
    },
    {
      "src": "{: { [1411,1412]",
      "dest": "{: { [2256,2257]"
    },
    {
      "src": "=: = [534,535]",
      "dest": "=: = [1130,1131]"
    },
    {
      "src": "constant: constant [589,597]",
      "dest": "constant: constant [1185,1193]"
    },
    {
      "src": "function: function [2353,2361]",
      "dest": "function: function [4478,4486]"
    },
    {
      "src": "primitive_type [582,588]",
      "dest": "primitive_type [1178,1184]"
    },
    {
      "src": "\": \" [706,707]",
      "dest": "\": \" [1302,1303]"
    },
    {
      "src": "function_body [1703,2232]",
      "dest": "function_body [4010,4357]"
    },
    {
      "src": "primitive_type [1580,1587]",
      "dest": "primitive_type [3351,3358]"
    },
    {
      "src": "identifier: sender [1995,2001]",
      "dest": "identifier: sender [3593,3599]"
    },
    {
      "src": "identifier: encodePacked [2552,2564]",
      "dest": "identifier: encodePacked [4676,4688]"
    },
    {
      "src": "string_literal [706,740]",
      "dest": "string_literal [1302,1336]"
    },
    {
      "src": ".: . [1852,1853]",
      "dest": ".: . [4887,4888]"
    },
    {
      "src": "emit: emit [2723,2727]",
      "dest": "emit: emit [4136,4140]"
    },
    {
      "src": "call_argument [1317,1337]",
      "dest": "call_argument [2162,2182]"
    },
    {
      "src": "parameter [1580,1598]",
      "dest": "parameter [3351,3368]"
    },
    {
      "src": "number_literal: 1 [1817,1818]",
      "dest": "number_literal: 1 [4124,4125]"
    },
    {
      "src": "uint256: uint256 [1071,1078]",
      "dest": "uint256: uint256 [1916,1923]"
    },
    {
      "src": ",: , [2079,2080]",
      "dest": ",: , [3688,3689]"
    },
    {
      "src": "parameter [939,946]",
      "dest": "parameter [1784,1791]"
    },
    {
      "src": "call_expression [1280,1338]",
      "dest": "call_expression [2125,2183]"
    },
    {
      "src": ",: , [2598,2599]",
      "dest": ",: , [4721,4722]"
    },
    {
      "src": "string: string [497,503]",
      "dest": "string: string [1093,1099]"
    },
    {
      "src": "call_argument [2616,2623]",
      "dest": "call_argument [4739,4746]"
    },
    {
      "src": ",: , [2772,2773]",
      "dest": ",: , [4177,4178]"
    },
    {
      "src": "return_statement [1273,1339]",
      "dest": "return_statement [2118,2184]"
    },
    {
      "src": "member_expression [1106,1142]",
      "dest": "member_expression [1951,1987]"
    },
    {
      "src": "type_name [2484,2491]",
      "dest": "type_name [4608,4615]"
    },
    {
      "src": "state_mutability [1388,1392]",
      "dest": "state_mutability [2233,2237]"
    },
    {
      "src": "member_expression [2762,2772]",
      "dest": "member_expression [4156,4166]"
    },
    {
      "src": "string_literal [2684,2712]",
      "dest": "string_literal [4807,4835]"
    },
    {
      "src": "function: function [875,883]",
      "dest": "function: function [1720,1728]"
    },
    {
      "src": "primitive_type [2484,2491]",
      "dest": "primitive_type [4608,4615]"
    },
    {
      "src": "type_name [582,588]",
      "dest": "type_name [1178,1184]"
    },
    {
      "src": "type_name [1580,1587]",
      "dest": "type_name [3351,3358]"
    },
    {
      "src": "return: return [1273,1279]",
      "dest": "return: return [2118,2124]"
    },
    {
      "src": "call_argument [2071,2079]",
      "dest": "call_argument [3680,3688]"
    },
    {
      "src": "identifier: payload [1883,1890]",
      "dest": "identifier: payload [4896,4903]"
    },
    {
      "src": "view: view [797,801]",
      "dest": "view: view [1642,1646]"
    },
    {
      "src": "call_argument [2048,2053]",
      "dest": "call_argument [3653,3658]"
    },
    {
      "src": "]: ] [861,862]",
      "dest": "]: ] [1706,1707]"
    },
    {
      "src": "type_name [1713,1720]",
      "dest": "type_name [4020,4027]"
    },
    {
      "src": "): ) [2431,2432]",
      "dest": "): ) [4555,4556]"
    },
    {
      "src": "call_argument [1785,1807]",
      "dest": "call_argument [4092,4114]"
    },
    {
      "src": "identifier: msgHash [982,989]",
      "dest": "identifier: msgHash [1827,1834]"
    },
    {
      "src": "identifier: nonce [2048,2053]",
      "dest": "identifier: nonce [3653,3658]"
    },
    {
      "src": "call_expression [837,853]",
      "dest": "call_expression [1682,1698]"
    },
    {
      "src": "comment: /**       Random slot storage elements and accessors.     */ [432,492]",
      "dest": "comment: /**       Random slot storage elements and accessors.     */ [1028,1088]"
    },
    {
      "src": "view: view [925,929]",
      "dest": "view: view [1770,1774]"
    },
    {
      "src": "string_literal [621,658]",
      "dest": "string_literal [1217,1254]"
    },
    {
      "src": ".: . [1440,1441]",
      "dest": ".: . [2285,2286]"
    },
    {
      "src": "parameter [771,786]",
      "dest": "parameter [1616,1631]"
    },
    {
      "src": "(: ( [1965,1966]",
      "dest": "(: ( [3559,3560]"
    },
    {
      "src": "identifier: msgHash [2670,2677]",
      "dest": "identifier: msgHash [4793,4800]"
    },
    {
      "src": "primitive_type [1060,1067]",
      "dest": "primitive_type [1905,1912]"
    },
    {
      "src": "call_expression [1729,1749]",
      "dest": "call_expression [4036,4056]"
    },
    {
      "src": "call_argument [1143,1163]",
      "dest": "call_argument [1988,2008]"
    },
    {
      "src": "override: override [1676,1684]",
      "dest": "override: override [3983,3991]"
    },
    {
      "src": "member_expression [1949,1965]",
      "dest": "member_expression [3543,3559]"
    },
    {
      "src": "\": \" [2684,2685]",
      "dest": "\": \" [4807,4808]"
    },
    {
      "src": "): ) [914,915]",
      "dest": "): ) [1759,1760]"
    },
    {
      "src": "): ) [1027,1028]",
      "dest": "): ) [1872,1873]"
    },
    {
      "src": "primitive_type [665,671]",
      "dest": "primitive_type [1261,1267]"
    },
    {
      "src": "state_variable_declaration [582,659]",
      "dest": "state_variable_declaration [1178,1255]"
    },
    {
      "src": "function_definition [747,869]",
      "dest": "function_definition [1592,1714]"
    },
    {
      "src": "function_definition [1177,1345]",
      "dest": "function_definition [2022,2190]"
    },
    {
      "src": "\": \" [106,107]",
      "dest": "\": \" [669,670]"
    },
    {
      "src": "primitive_type [1694,1701]",
      "dest": "primitive_type [4001,4008]"
    },
    {
      "src": "): ) [1701,1702]",
      "dest": "): ) [4008,4009]"
    },
    {
      "src": "(: ( [1990,1991]",
      "dest": "(: ( [3588,3589]"
    },
    {
      "src": "(: ( [770,771]",
      "dest": "(: ( [1615,1616]"
    },
    {
      "src": "identifier: msg [2587,2590]",
      "dest": "identifier: msg [4710,4713]"
    },
    {
      "src": "[: [ [2412,2413]",
      "dest": "[: [ [4536,4537]"
    },
    {
      "src": "return_type_definition [1217,1262]",
      "dest": "return_type_definition [2062,2107]"
    },
    {
      "src": "): ) [2491,2492]",
      "dest": "): ) [4615,4616]"
    },
    {
      "src": "constant: constant [672,680]",
      "dest": "constant: constant [1268,1276]"
    },
    {
      "src": "solidity: solidity [47,55]",
      "dest": "solidity: solidity [643,651]"
    },
    {
      "src": "bytes32: bytes32 [1234,1241]",
      "dest": "bytes32: bytes32 [2079,2086]"
    },
    {
      "src": "): ) [818,819]",
      "dest": "): ) [1663,1664]"
    },
    {
      "src": "]: ] [2194,2195]",
      "dest": "]: ] [4319,4320]"
    },
    {
      "src": "\": \" [2711,2712]",
      "dest": "\": \" [4834,4835]"
    },
    {
      "src": "call_expression [2548,2624]",
      "dest": "call_expression [4672,4747]"
    },
    {
      "src": "string [73,97]",
      "dest": "string [702,720]"
    },
    {
      "src": "identifier: to_address [1588,1598]",
      "dest": "identifier: toAddress [3359,3368]"
    },
    {
      "src": "function_definition [1546,2232]",
      "dest": "function_definition [3854,4357]"
    },
    {
      "src": "external: external [1667,1675]",
      "dest": "external: external [3974,3982]"
    },
    {
      "src": "function: function [1351,1359]",
      "dest": "function: function [2196,2204]"
    },
    {
      "src": "return_statement [2211,2226]",
      "dest": "return_statement [4336,4351]"
    },
    {
      "src": "identifier: msgHash [2515,2522]",
      "dest": "identifier: msgHash [4639,4646]"
    },
    {
      "src": "}: } [2231,2232]",
      "dest": "}: } [4356,4357]"
    },
    {
      "src": "uint256: uint256 [1983,1990]",
      "dest": "uint256: uint256 [3581,3588]"
    },
    {
      "src": "parameter [811,818]",
      "dest": "parameter [1656,1663]"
    },
    {
      "src": ".: . [2551,2552]",
      "dest": ".: . [4675,4676]"
    },
    {
      "src": "primitive_type [811,818]",
      "dest": "primitive_type [1656,1663]"
    },
    {
      "src": "parameter [2405,2431]",
      "dest": "parameter [4529,4555]"
    },
    {
      "src": "external: external [916,924]",
      "dest": "external: external [1761,1769]"
    },
    {
      "src": "array_access [965,990]",
      "dest": "array_access [1810,1835]"
    },
    {
      "src": "returns: returns [2475,2482]",
      "dest": "returns: returns [4599,4606]"
    },
    {
      "src": "(: ( [2586,2587]",
      "dest": "(: ( [4709,4710]"
    },
    {
      "src": "number_literal: 1 [2199,2200]",
      "dest": "number_literal: 1 [4324,4325]"
    },
    {
      "src": "comment: /**   Implements sending messages to L2 by adding them to a pipe and consuming messages from L2 by   removing them from a different pipe. A deriving contract can handle the former pipe and add items   to the latter pipe while interacting with L2. */ [127,376]",
      "dest": "comment: /**   Implements sending messages to L2 by adding them to a pipe and consuming messages from L2 by   removing them from a different pipe. A deriving contract can handle the former pipe and add items   to the latter pipe while interacting with L2. */ [723,972]"
    }
  ],
  "actions": [
    {
      "action": "move-tree",
      "tree": "import_directive [66,98]",
      "parent": "source_file [0,6418]",
      "at": 3
    },
    {
      "action": "insert-node",
      "tree": "comment: /*   Copyright 2019-2022 StarkWare Industries Ltd.    Licensed under the Apache License, Version 2.0 (the \"License\").   You may not use this file except in compliance with the License.   You may obtain a copy of the License at    https://www.starkware.co/open-source-license/    Unless required by applicable law or agreed to in writing,   software distributed under the License is distributed on an \"AS IS\" BASIS,   WITHOUT WARRANTIES OR CONDITIONS OF ANY KIND, either express or implied.   See the License for the specific language governing permissions   and limitations under the License. */ [0,595]",
      "parent": "source_file [0,6418]",
      "at": 0
    },
    {
      "action": "insert-tree",
      "tree": "state_variable_declaration [1343,1462]",
      "parent": "contract_body [1022,6417]",
      "at": 5
    },
    {
      "action": "insert-tree",
      "tree": "state_variable_declaration [1468,1586]",
      "parent": "contract_body [1022,6417]",
      "at": 6
    },
    {
      "action": "insert-tree",
      "tree": "function_definition [2335,2487]",
      "parent": "contract_body [1022,6417]",
      "at": 12
    },
    {
      "action": "insert-node",
      "tree": "function_definition [2493,2655]",
      "parent": "contract_body [1022,6417]",
      "at": 13
    },
    {
      "action": "insert-node",
      "tree": "comment: /**       Returns the timestamp at the time cancelL1ToL2Message was called with a message       matching 'msgHash'.        The function returns 0 if cancelL1ToL2Message was never called.     */ [2661,2854]",
      "parent": "contract_body [1022,6417]",
      "at": 14
    },
    {
      "action": "insert-tree",
      "tree": "function_definition [2859,3005]",
      "parent": "contract_body [1022,6417]",
      "at": 15
    },
    {
      "action": "insert-tree",
      "tree": "function_definition [3011,3232]",
      "parent": "contract_body [1022,6417]",
      "at": 16
    },
    {
      "action": "insert-node",
      "tree": "comment: /**       Returns the hash of an L1 -> L2 message from msg.sender.     */ [3238,3311]",
      "parent": "contract_body [1022,6417]",
      "at": 17
    },
    {
      "action": "insert-node",
      "tree": "function_definition [3316,3792]",
      "parent": "contract_body [1022,6417]",
      "at": 18
    },
    {
      "action": "insert-tree",
      "tree": "function_definition [4981,5513]",
      "parent": "contract_body [1022,6417]",
      "at": 23
    },
    {
      "action": "insert-tree",
      "tree": "function_definition [5519,6415]",
      "parent": "contract_body [1022,6417]",
      "at": 24
    },
    {
      "action": "insert-node",
      "tree": "function: function [2493,2501]",
      "parent": "function_definition [2493,2655]",
      "at": 0
    },
    {
      "action": "insert-node",
      "tree": "identifier: messageCancellationDelay [2502,2526]",
      "parent": "function_definition [2493,2655]",
      "at": 1
    },
    {
      "action": "insert-node",
      "tree": "(: ( [2526,2527]",
      "parent": "function_definition [2493,2655]",
      "at": 2
    },
    {
      "action": "move-tree",
      "tree": "parameter [2383,2403]",
      "parent": "function_definition [2493,2655]",
      "at": 3
    },
    {
      "action": "insert-node",
      "tree": "): ) [2549,2550]",
      "parent": "function_definition [2493,2655]",
      "at": 4
    },
    {
      "action": "insert-tree",
      "tree": "visibility [2551,2559]",
      "parent": "function_definition [2493,2655]",
      "at": 5
    },
    {
      "action": "insert-tree",
      "tree": "function_body [2560,2655]",
      "parent": "function_definition [2493,2655]",
      "at": 6
    },
    {
      "action": "insert-node",
      "tree": "function: function [3316,3324]",
      "parent": "function_definition [3316,3792]",
      "at": 0
    },
    {
      "action": "insert-node",
      "tree": "identifier: getL1ToL2MsgHash [3325,3341]",
      "parent": "function_definition [3316,3792]",
      "at": 1
    },
    {
      "action": "insert-node",
      "tree": "(: ( [3341,3342]",
      "parent": "function_definition [3316,3792]",
      "at": 2
    },
    {
      "action": "move-tree",
      "tree": "parameter [1580,1598]",
      "parent": "function_definition [3316,3792]",
      "at": 3
    },
    {
      "action": "insert-node",
      "tree": ",: , [3368,3369]",
      "parent": "function_definition [3316,3792]",
      "at": 4
    },
    {
      "action": "insert-tree",
      "tree": "parameter [3378,3394]",
      "parent": "function_definition [3316,3792]",
      "at": 5
    },
    {
      "action": "insert-node",
      "tree": ",: , [3394,3395]",
      "parent": "function_definition [3316,3792]",
      "at": 6
    },
    {
      "action": "insert-tree",
      "tree": "parameter [3404,3430]",
      "parent": "function_definition [3316,3792]",
      "at": 7
    },
    {
      "action": "insert-node",
      "tree": ",: , [3430,3431]",
      "parent": "function_definition [3316,3792]",
      "at": 8
    },
    {
      "action": "insert-tree",
      "tree": "parameter [3440,3453]",
      "parent": "function_definition [3316,3792]",
      "at": 9
    },
    {
      "action": "insert-node",
      "tree": "): ) [3458,3459]",
      "parent": "function_definition [3316,3792]",
      "at": 10
    },
    {
      "action": "insert-tree",
      "tree": "visibility [3460,3468]",
      "parent": "function_definition [3316,3792]",
      "at": 11
    },
    {
      "action": "insert-tree",
      "tree": "return_type_definition [3469,3486]",
      "parent": "function_definition [3316,3792]",
      "at": 12
    },
    {
      "action": "insert-node",
      "tree": "function_body [3487,3792]",
      "parent": "function_definition [3316,3792]",
      "at": 13
    },
    {
      "action": "insert-tree",
      "tree": "parameter [3888,3905]",
      "parent": "function_definition [3854,4357]",
      "at": 3
    },
    {
      "action": "insert-tree",
      "tree": "parameter [4508,4527]",
      "parent": "function_definition [4478,4975]",
      "at": 3
    },
    {
      "action": "update-node",
      "tree": "identifier: from_address [2391,2403]",
      "label": "delayInSeconds"
    },
    {
      "action": "update-node",
      "tree": "identifier: to_address [1588,1598]",
      "label": "toAddress"
    },
    {
      "action": "insert-node",
      "tree": "{: { [3487,3488]",
      "parent": "function_body [3487,3792]",
      "at": 0
    },
    {
      "action": "insert-node",
      "tree": "return_statement [3497,3786]",
      "parent": "function_body [3487,3792]",
      "at": 1
    },
    {
      "action": "insert-node",
      "tree": "}: } [3791,3792]",
      "parent": "function_body [3487,3792]",
      "at": 2
    },
    {
      "action": "move-tree",
      "tree": "emit_statement [2723,2783]",
      "parent": "function_body [4010,4357]",
      "at": 3
    },
    {
      "action": "move-tree",
      "tree": ",: , [2760,2761]",
      "parent": "emit_statement [4136,4205]",
      "at": 5
    },
    {
      "action": "move-tree",
      "tree": "call_argument [2748,2760]",
      "parent": "emit_statement [4136,4205]",
      "at": 5
    },
    {
      "action": "move-tree",
      "tree": "emit_statement [1829,1899]",
      "parent": "function_body [4621,4975]",
      "at": 3
    },
    {
      "action": "move-tree",
      "tree": ",: , [1859,1860]",
      "parent": "emit_statement [4846,4905]",
      "at": 5
    },
    {
      "action": "move-tree",
      "tree": "call_argument [1849,1859]",
      "parent": "emit_statement [4846,4905]",
      "at": 5
    },
    {
      "action": "insert-node",
      "tree": "return: return [3497,3503]",
      "parent": "return_statement [3497,3786]",
      "at": 0
    },
    {
      "action": "move-tree",
      "tree": "call_expression [1926,2160]",
      "parent": "return_statement [3497,3786]",
      "at": 1
    },
    {
      "action": "update-node",
      "tree": "identifier: ConsumedMessageToL1 [2728,2747]",
      "label": "LogMessageToL2"
    },
    {
      "action": "move-tree",
      "tree": "call_argument [1873,1881]",
      "parent": "emit_statement [4136,4205]",
      "at": 7
    },
    {
      "action": "insert-node",
      "tree": ",: , [4187,4188]",
      "parent": "emit_statement [4136,4205]",
      "at": 8
    },
    {
      "action": "insert-node",
      "tree": ",: , [4196,4197]",
      "parent": "emit_statement [4136,4205]",
      "at": 10
    },
    {
      "action": "move-tree",
      "tree": "call_argument [1892,1897]",
      "parent": "emit_statement [4136,4205]",
      "at": 11
    },
    {
      "action": "insert-tree",
      "tree": "call_expression [4232,4285]",
      "parent": "variable_declaration_statement [4214,4286]",
      "at": 2
    },
    {
      "action": "update-node",
      "tree": "identifier: LogMessageToL2 [1834,1848]",
      "label": "ConsumedMessageToL1"
    },
    {
      "action": "update-node",
      "tree": "identifier: from_address [2748,2760]",
      "label": "toAddress"
    },
    {
      "action": "update-node",
      "tree": "identifier: to_address [1861,1871]",
      "label": "fromAddress"
    },
    {
      "action": "update-node",
      "tree": "identifier: to_address [2020,2030]",
      "label": "toAddress"
    },
    {
      "action": "update-node",
      "tree": "identifier: from_address [2565,2577]",
      "label": "fromAddress"
    },
    {
      "action": "delete-node",
      "tree": ",: , [1881,1882]"
    },
    {
      "action": "delete-node",
      "tree": ",: , [1890,1891]"
    }
  ]
}